{
	"config": "flex",
	"type": "app",
	"mainClass": "GAME",
	"compilerOptions": {
		"output": "bin/bymr-stable.swf",
		"target-player": "11.0",
		"swf-version": 13,
		"default-frame-rate": 40,
		"default-background-color": "#FFFFFF",
		"default-size": {
			"width": 760,
			"height": 670
		},
		"optimize": true,
		"debug": false,
		"strict": false,
		"warnings": false,
		"use-network": true,
		"advanced-telemetry": true,
		"static-link-runtime-shared-libraries": true,
		"source-path": [
			"client/scripts"
		],
		"library-path": [
			"./playerglobal.swc"
		]
	}
}